LICENSE
README.md
kbinxml
setup.cfg
setup.py
kbinxml/__init__.py
kbinxml/bytebuffer.py
kbinxml/format_ids.py
kbinxml/kbinxml.py
kbinxml/sixbit.py
kbinxml/test.py
kbinxml.egg-info/PKG-INFO
kbinxml.egg-info/SOURCES.txt
kbinxml.egg-info/dependency_links.txt
kbinxml.egg-info/entry_points.txt
kbinxml.egg-info/requires.txt
kbinxml.egg-info/top_level.txt